preqs/NOTICE
preqs/__init__.py
preqs/_version.py
preqs/preqs.py
preqs-0.1.0b1.dist-info/LICENSE
preqs-0.1.0b1.dist-info/METADATA
preqs-0.1.0b1.dist-info/WHEEL
preqs-0.1.0b1.dist-info/entry_points.txt
preqs-0.1.0b1.dist-info/top_level.txt
preqs-0.1.0b1.dist-info/RECORD
