Metadata-Version: 2.1
Name: preqs
Version: 0.1.0b1
Summary: A simple (and fast) requirements.txt file generator.
Author-email: The Developers <development@s3dev.uk>
License: GNU GPL-3
Project-URL: Homepage, https://github.com/s3dev/preqs
Project-URL: Repository, https://github.com/s3dev/preqs
Keywords: build,development,requirements,setup,utilities
Classifier: Development Status :: 4 - Beta
Classifier: Intended Audience :: Developers
Classifier: License :: OSI Approved :: MIT License
Classifier: Operating System :: POSIX :: Linux
Classifier: Operating System :: Microsoft :: Windows
Classifier: Programming Language :: Python :: 3.6
Classifier: Programming Language :: Python :: 3.7
Classifier: Programming Language :: Python :: 3.8
Classifier: Programming Language :: Python :: 3.9
Classifier: Programming Language :: Python :: 3.10
Classifier: Programming Language :: Python :: 3.11
Classifier: Programming Language :: Python :: 3.12
Classifier: Topic :: Software Development
Classifier: Topic :: Utilities
Requires-Python: >=3.6
License-File: LICENSE
